visionlog/__init__.py
visionlog/cli.py
visionlog/visionlog.py
visionlog-0.1.1.dist-info/LICENSE
visionlog-0.1.1.dist-info/METADATA
visionlog-0.1.1.dist-info/WHEEL
visionlog-0.1.1.dist-info/entry_points.txt
visionlog-0.1.1.dist-info/RECORD
