Metadata-Version: 2.1
Name: visionlog
Version: 0.1.1
Summary: A universal structured logging library for analytics tracking
Home-page: https://github.com/szmyty/visionlog
License: MIT
Author: Alan Szmyt
Author-email: szmyty@gmail.com
Requires-Python: >=3.8,<4.0
Classifier: License :: OSI Approved :: MIT License
Classifier: Programming Language :: Python :: 3
Classifier: Programming Language :: Python :: 3.8
Classifier: Programming Language :: Python :: 3.9
Classifier: Programming Language :: Python :: 3.10
Classifier: Programming Language :: Python :: 3.11
Classifier: Programming Language :: Python :: 3.12
Requires-Dist: click (>=8.1.3,<9.0.0)
Requires-Dist: device-detector (>=5.0.1,<6.0.0)
Requires-Dist: loguru (>=0.7.0,<0.8.0)
Requires-Dist: opentelemetry-api (>=1.15.0,<2.0.0)
Requires-Dist: opentelemetry-sdk (>=1.15.0,<2.0.0)
Requires-Dist: orjson (>=3.8.1,<4.0.0)
Requires-Dist: requests (>=2.32.3,<3.0.0)
Requires-Dist: structlog (>=23.1.0,<24.0.0)
Project-URL: Documentation, https://github.com/szmyty/visionlog#readme
Project-URL: Repository, https://github.com/szmyty/visionlog
